core/__init__.py
core/models.py
core/utils.py
sashimi-0.0.2.dist-info/LICENSE
sashimi-0.0.2.dist-info/METADATA
sashimi-0.0.2.dist-info/WHEEL
sashimi-0.0.2.dist-info/top_level.txt
sashimi-0.0.2.dist-info/RECORD
