Metadata-Version: 2.1
Name: sashimi
Version: 0.0.2
Summary: Python library for benchmarking spatio-temporal saliency prediction on videos (tracking where eyes are looking at)
Home-page: https://github.com/doerlbh/sashimi
Author: Baihan Lin
Author-email: doerlbh@gmail.com
License: GPLv3
Project-URL: Bug Tracker, https://github.com/doerlbh/sashimi/issues
Classifier: Programming Language :: Python :: 3
Classifier: License :: OSI Approved :: GNU General Public License v3 (GPLv3)
Classifier: Operating System :: OS Independent
Requires-Python: >=3.6
License-File: LICENSE
Requires-Dist: numpy (>=1.16.5)
Requires-Dist: pandas
